koza/__init__.py
koza/app.py
koza/cli_utils.py
koza/converter/__init__.py
koza/converter/biolink_converter.py
koza/converter/kgx_converter.py
koza/io/__init__.py
koza/io/reader/__init__.py
koza/io/reader/csv_reader.py
koza/io/reader/json_reader.py
koza/io/reader/jsonl_reader.py
koza/io/utils.py
koza/io/writer/__init__.py
koza/io/writer/jsonl_writer.py
koza/io/writer/tsv_writer.py
koza/io/writer/writer.py
koza/io/yaml_loader.py
koza/main.py
koza/model/__init__.py
koza/model/config/__init__.py
koza/model/config/pydantic_config.py
koza/model/config/source_config.py
koza/model/config/sssom_config.py
koza/model/curie_cleaner.py
koza/model/map_dict.py
koza/model/source.py
koza/model/translation_table.py
koza/utils/__init__
koza/utils/exceptions.py
koza/utils/log_utils.py
koza/utils/row_filter.py
koza/utils/testing_utils.py
koza-0.7.1.dist-info/LICENSE
koza-0.7.1.dist-info/METADATA
koza-0.7.1.dist-info/WHEEL
koza-0.7.1.dist-info/entry_points.txt
koza-0.7.1.dist-info/RECORD
