Metadata-Version: 2.1
Name: koza
Version: 0.7.1
Summary: Data transformation framework for LinkML data models
License: BSD License
Author: The Monarch Initiative
Author-email: info@monarchinitiative.org
Requires-Python: >=3.9,<4.0
Classifier: License :: Other/Proprietary License
Classifier: Programming Language :: Python :: 3
Classifier: Programming Language :: Python :: 3.9
Classifier: Programming Language :: Python :: 3.10
Classifier: Programming Language :: Python :: 3.11
Classifier: Programming Language :: Python :: 3.12
Requires-Dist: duckdb
Requires-Dist: linkml (>=1.7.8)
Requires-Dist: loguru
Requires-Dist: ordered-set (>=4.1.0)
Requires-Dist: pydantic (>=2.4,<3.0)
Requires-Dist: pyyaml (>=5.0.0)
Requires-Dist: requests (>=2.24.0,<3.0.0)
Requires-Dist: sssom (>=0.4)
Requires-Dist: typer (>=0.12.3)
